{
  "$schema": "https://developer.microsoft.com/json-schemas/spfx-build/package-solution.schema.json",
  "solution": {
    "name": "it-hit-web-dav-share-point-extension-3-client-side-solution",
    "id": "b9a85d72-e113-4959-90f9-e0b9bd667570",
    "version": "1.0.0.0",
    "includeClientSideAssets": true,
    "isDomainIsolated": false,
    "developer": {
      "name": "",
      "websiteUrl": "",
      "privacyUrl": "",
      "termsOfUseUrl": "",
      "mpnId": ""
    },
    "features": [
      {
        "title": "Application Extension - Deployment of custom action.",
        "description": "Deploys a custom action with ClientSideComponentId association",
        "id": "9296d8a1-04f6-41b2-b02d-c9d94a3ac2dd",
        "version": "1.0.0.0",
        "assets": {
          "elementManifests": [
            "elements.xml",
            "ClientSideInstance.xml"
          ]
        }
      }
    ]
  },
  "paths": {
    "zippedPackage": "solution/it-hit-web-dav-share-point-extension-3.sppkg"
  }
}
